README.rst
setup.py
dataholder/__init__.py
dataholder.egg-info/PKG-INFO
dataholder.egg-info/SOURCES.txt
dataholder.egg-info/dependency_links.txt
dataholder.egg-info/top_level.txt