Metadata-Version: 1.1
Name: dataholder
Version: 1.0.1
Summary: Trick for assignment in an if statement
Home-page: https://github.com/pitcons/dataholder
Author: UNKNOWN
Author-email: UNKNOWN
License: UNKNOWN
Keywords: python
Platform: UNKNOWN
Classifier: Development Status :: 5 - Production/Stable
Classifier: Intended Audience :: Developers
Classifier: Natural Language :: English
Classifier: License :: OSI Approved :: MIT License
Classifier: Programming Language :: Python
Classifier: Programming Language :: Python :: 2.7
Classifier: Programming Language :: Python :: 3.3
